mbpluginloader/__init__.py
mbpluginloader/loader.py
mbpluginloader/pyd/20000/mbpluginload.pyd
mbpluginloader/pyd/22000/mbpluginload.pyd
mbpluginloader/pyd/23000/mbpluginload.pyd
mbpluginloader/pyd/24000/mbpluginload.pyd
mbpluginloader/pyd/25000/mbpluginload.pyd
mbpluginloader/pyd/26000/mbpluginload.pyd
mbpluginloader-2.1.dist-info/licenses/LICENSE
mbpluginloader-2.1.dist-info/METADATA
mbpluginloader-2.1.dist-info/WHEEL
mbpluginloader-2.1.dist-info/top_level.txt
mbpluginloader-2.1.dist-info/RECORD
