Metadata-Version: 2.4
Name: mbpluginloader
Version: 2.1
Summary: Custom MotionBuilder Module to load C++ plugins from Python Project on Startup
Author: Ndgt
License-Expression: BSD-3-Clause
Classifier: Operating System :: Microsoft :: Windows
Classifier: Intended Audience :: Developers
Requires-Python: >=2.7
License-File: LICENSE
Dynamic: license-file
